xboxoneexternal.py
xbox_drive_converter-1.0.0.dist-info/METADATA
xbox_drive_converter-1.0.0.dist-info/WHEEL
xbox_drive_converter-1.0.0.dist-info/licenses/LICENSE
xbox_drive_converter-1.0.0.dist-info/RECORD
