Metadata-Version: 2.1
Name: xbox_drive_converter
Version: 1.0.0
Summary: A tool for converting external drives between PC and Xbox One/Series
Project-URL: Homepage, https://github.com/Zopolis4/xboxoneexternal
Project-URL: Bug Tracker, https://github.com/Zopolis4/xboxoneexternal/issues
Author-email: Maximilian Downey Twiss <creatorsmithmdt@gmail.com>
License: The MIT License (MIT)
Classifier: License :: OSI Approved :: MIT License
Classifier: Operating System :: OS Independent
Classifier: Programming Language :: Python :: 3
Requires-Python: >=3.7
